Metadata-Version: 2.1
Name: pattern-clustering
Version: 1.0.0
Summary: This tool clusterizes lines of text given a collection of input patterns modeled using regular expressions.
Home-page: https://github.com/nokia/pattern-clustering
Author: Marc-Olivier Buob, Maxime Raynal
Author-email: marc-olivier.buob@nokia-bell-labs.com, maxime.raynal@nokia.com
License: BSD license
Keywords: pattern_clustering
Platform: UNKNOWN
Classifier: Development Status :: 2 - Pre-Alpha
Classifier: Intended Audience :: Developers
Classifier: License :: OSI Approved :: BSD License
Classifier: Natural Language :: English
Classifier: Programming Language :: Python :: 3
Requires-Python: >=3.6
License-File: LICENSE
License-File: AUTHORS.rst
